outeai/__init__.py
outeai/_client.py
outeai/_exceptions.py
outeai/_models.py
outeai/_api/__init__.py
outeai/_api/generate.py
outeai-1.0.0.dist-info/licenses/LICENSE
outeai-1.0.0.dist-info/METADATA
outeai-1.0.0.dist-info/WHEEL
outeai-1.0.0.dist-info/top_level.txt
outeai-1.0.0.dist-info/RECORD
