Metadata-Version: 2.4
Name: outeai
Version: 1.0.0
Summary: OuteAI
Home-page: https://github.com/edwko/OuteAI
Author: OuteAI
Classifier: Programming Language :: Python :: 3
Classifier: License :: OSI Approved :: Apache Software License
Classifier: Operating System :: OS Independent
Requires-Python: >=3.9
License-File: LICENSE
Requires-Dist: requests
Requires-Dist: httpx
Requires-Dist: numpy
Requires-Dist: loguru
Requires-Dist: tqdm
Dynamic: author
Dynamic: classifier
Dynamic: description
Dynamic: description-content-type
Dynamic: home-page
Dynamic: license-file
Dynamic: requires-dist
Dynamic: requires-python
Dynamic: summary
